MLB/__init__.py
MLB/mlb_tabular_2class.py
MLB-0.0.7.dist-info/METADATA
MLB-0.0.7.dist-info/WHEEL
MLB-0.0.7.dist-info/top_level.txt
MLB-0.0.7.dist-info/RECORD
